xes_neo
