Metadata-Version: 2.4
Name: xes_neo
Version: 0.0.19
Summary: XES Analysis using GA
Home-page: https://github.com/lanl/XES_Neo_Public.git
Download-URL: https://github.com/lanl/XES_Neo_Public/tarball/main
Author: Alaina Humiston, Miu Lun Lau, Jeff Terry, Min Long
Author-email: athompson9@hawk.iit.edu, andylau@u.boisestate.edu, jterry98@iit.edu, minlong@boisestate.edu
License: GPLv3
Keywords: GA,XES,analysis
License-File: LICENSE.md
Requires-Dist: numpy
Requires-Dist: numba
Requires-Dist: attrs
Requires-Dist: matplotlib
Requires-Dist: scipy
Requires-Dist: psutil
Dynamic: author
Dynamic: author-email
Dynamic: description
Dynamic: download-url
Dynamic: home-page
Dynamic: keywords
Dynamic: license
Dynamic: license-file
Dynamic: requires-dist
Dynamic: summary
